pyclitable/__init__.py
pyclitable/pyCliTable.py
pyclitable/style.py
pyclitable/test.py
pyclitable-0.0.5.dist-info/METADATA
pyclitable-0.0.5.dist-info/WHEEL
pyclitable-0.0.5.dist-info/licenses/LICENSE
pyclitable-0.0.5.dist-info/RECORD
