Metadata-Version: 2.1
Name: pyCliTable
Version: 0.0.5
Summary: A package designed to simplify the display of data in a tabular format.
Project-URL: Homepage, https://github.com/babucarr32/pyCliTable
Project-URL: Issues, https://github.com/babucarr32/pyCliTable/issues
Author-email: Baboucarr <bbabucarr32@gmail.com>
License-File: LICENSE
Classifier: License :: OSI Approved :: MIT License
Classifier: Operating System :: OS Independent
Classifier: Programming Language :: Python :: 3
Requires-Python: >=2.7
